typedlogic/__init__.py
typedlogic/builtins.py
typedlogic/cli.py
typedlogic/compiler.py
typedlogic/compilers/__init__.py
typedlogic/compilers/fol_compiler.py
typedlogic/compilers/prolog_compiler.py
typedlogic/compilers/prover9_compiler.py
typedlogic/compilers/sexpr_compiler.py
typedlogic/compilers/tptp_compiler.py
typedlogic/compilers/yaml_compiler.py
typedlogic/datamodel.py
typedlogic/datamodels/__init__.py
typedlogic/datamodels/typesystem.py
typedlogic/decorators.py
typedlogic/evaluation.py
typedlogic/extensions/__init__.py
typedlogic/extensions/probabilistic.py
typedlogic/generators.py
typedlogic/integrations/__init__.py
typedlogic/integrations/data/__init__.py
typedlogic/integrations/data/dask/__init__.py
typedlogic/integrations/data/ibis/__init__.py
typedlogic/integrations/data/pandas/__init__.py
typedlogic/integrations/data/polars/__init__.py
typedlogic/integrations/data/sqlmodel/__init__.py
typedlogic/integrations/frameworks/__init__.py
typedlogic/integrations/frameworks/hornedowl/__init__.py
typedlogic/integrations/frameworks/hornedowl/horned_owl_bridge.py
typedlogic/integrations/frameworks/hornedowl/owl_compiler.py
typedlogic/integrations/frameworks/hornedowl/owl_parser.py
typedlogic/integrations/frameworks/linkml/__init__.py
typedlogic/integrations/frameworks/linkml/instance.py
typedlogic/integrations/frameworks/linkml/loader.py
typedlogic/integrations/frameworks/linkml/meta.py
typedlogic/integrations/frameworks/linkml/meta_axioms.py
typedlogic/integrations/frameworks/linkml/validator.py
typedlogic/integrations/frameworks/owldl/__init__.py
typedlogic/integrations/frameworks/owldl/ontology_generators.py
typedlogic/integrations/frameworks/owldl/owl_from_fol.py
typedlogic/integrations/frameworks/owldl/owlpy_compiler.py
typedlogic/integrations/frameworks/owldl/owlpy_parser.py
typedlogic/integrations/frameworks/owldl/owltop.py
typedlogic/integrations/frameworks/owldl/reasoner.py
typedlogic/integrations/frameworks/pandas/__init__.py
typedlogic-0.2.0.dist-info/LICENSE
typedlogic-0.2.0.dist-info/METADATA
typedlogic-0.2.0.dist-info/WHEEL
typedlogic-0.2.0.dist-info/entry_points.txt
typedlogic-0.2.0.dist-info/RECORD
