Metadata-Version: 2.3
Name: typedlogic
Version: 0.2.0
Summary: typedlogic
License: MIT
Author: Author 1
Author-email: author@org.org
Requires-Python: >=3.10,<4.0
Classifier: License :: OSI Approved :: MIT License
Classifier: Programming Language :: Python :: 3
Classifier: Programming Language :: Python :: 3.10
Classifier: Programming Language :: Python :: 3.11
Classifier: Programming Language :: Python :: 3.12
Classifier: Programming Language :: Python :: 3.13
Provides-Extra: clingo
Provides-Extra: clorm
Provides-Extra: gavel-owl
Provides-Extra: llm
Provides-Extra: owl
Provides-Extra: pandas
Provides-Extra: pandera
Provides-Extra: problog
Provides-Extra: pydantic
Provides-Extra: pyprover
Provides-Extra: rdflib
Provides-Extra: snakelog
Provides-Extra: sympy
Provides-Extra: tests
Provides-Extra: z3
Requires-Dist: clingo ; extra == "clingo"
Requires-Dist: clorm ; extra == "clorm"
Requires-Dist: gavel-owl ; extra == "gavel-owl"
Requires-Dist: importlib-metadata (>=8.2.0)
Requires-Dist: llm ; extra == "llm"
Requires-Dist: pandas ; extra == "pandas"
Requires-Dist: pandera[mypy] ; extra == "pandera"
Requires-Dist: ply ; extra == "gavel-owl"
Requires-Dist: problog ; extra == "problog"
Requires-Dist: py-horned-owl (>=1.0.0,<2.0.0,!=1.0.1) ; extra == "owl"
Requires-Dist: pydantic ; extra == "pydantic"
Requires-Dist: pyprover ; extra == "pyprover"
Requires-Dist: rdflib ; extra == "rdflib"
Requires-Dist: snakelog ; extra == "snakelog"
Requires-Dist: sympy ; extra == "sympy"
Requires-Dist: typer (>=0.12.5,<0.13.0)
Requires-Dist: z3-solver ; extra == "z3"
